geocat.f2py-2023.3.0-py3.11-nspkg.pth
geocat/f2py/__init__.py
geocat/f2py/checks.py
geocat/f2py/errors.py
geocat/f2py/linint2_wrapper.py
geocat/f2py/missing_values.py
geocat/f2py/moc_globe_atl_wrapper.py
geocat/f2py/rcm2points_wrapper.py
geocat/f2py/rcm2rgrid_wrapper.py
geocat/f2py/triple_to_grid_wrapper.py
geocat/f2py/fortran/__init__.py
geocat/f2py/fortran/grid2triple.f
geocat/f2py/fortran/grid2triple.pyf
geocat/f2py/fortran/linint2.f
geocat/f2py/fortran/linint2.pyf
geocat/f2py/fortran/linmsg_dp.f
geocat/f2py/fortran/moc_loops.f
geocat/f2py/fortran/moc_loops.pyf
geocat/f2py/fortran/rcm2points.f
geocat/f2py/fortran/rcm2points.pyf
geocat/f2py/fortran/rcm2rgrid.f
geocat/f2py/fortran/rcm2rgrid.pyf
geocat/f2py/fortran/triple2grid.f
geocat/f2py/fortran/triple2grid.pyf
geocat/f2py/fortran/all_todo/KolmSmir2.f
geocat/f2py/fortran/all_todo/README
geocat/f2py/fortran/all_todo/VSPCORR.f
geocat/f2py/fortran/all_todo/aam.f
geocat/f2py/fortran/all_todo/accumrun.f
geocat/f2py/fortran/all_todo/areaAve.f
geocat/f2py/fortran/all_todo/areaAve2.f
geocat/f2py/fortran/all_todo/areaRmse.f
geocat/f2py/fortran/all_todo/areaRmse2.f
geocat/f2py/fortran/all_todo/areaSum2.f
geocat/f2py/fortran/all_todo/area_conremap.f
geocat/f2py/fortran/all_todo/bfilter1.f
geocat/f2py/fortran/all_todo/binavg.f
geocat/f2py/fortran/all_todo/bindata.f
geocat/f2py/fortran/all_todo/calc_uh.f90
geocat/f2py/fortran/all_todo/calcorc_dp.f
geocat/f2py/fortran/all_todo/cancor.f
geocat/f2py/fortran/all_todo/cdf_dp.f
geocat/f2py/fortran/all_todo/cdft_dp.f
geocat/f2py/fortran/all_todo/cfft_driver.f
geocat/f2py/fortran/all_todo/cfftb.f
geocat/f2py/fortran/all_todo/cfftb1.f
geocat/f2py/fortran/all_todo/cfftf.f
geocat/f2py/fortran/all_todo/cfftf1.f
geocat/f2py/fortran/all_todo/cffti.f
geocat/f2py/fortran/all_todo/cffti1.f
geocat/f2py/fortran/all_todo/chiin_dp.f
geocat/f2py/fortran/all_todo/cntrFiniteDiff.f
geocat/f2py/fortran/all_todo/conservLinInt_2d_ncl.f
geocat/f2py/fortran/all_todo/covcorm_driver.f
geocat.f2py-2023.3.0.dist-info/LICENSE
geocat.f2py-2023.3.0.dist-info/METADATA
geocat.f2py-2023.3.0.dist-info/WHEEL
geocat.f2py-2023.3.0.dist-info/namespace_packages.txt
geocat.f2py-2023.3.0.dist-info/top_level.txt
geocat.f2py-2023.3.0.dist-info/RECORD
