Metadata-Version: 2.1
Name: geocat.f2py
Version: 2023.3.0
Summary: GeoCAT-f2py wraps, in Python, the compiled language
Home-page: https://github.com/NCAR/geocat-f2py
Maintainer: GeoCAT
Maintainer-email: geocat@ucar.edu
Project-URL: Documentation, https://geocat-f2py.readthedocs.io
Project-URL: Source, https://github.com/NCAR/geocat-f2py
Project-URL: Tracker, https://github.com/NCAR/geocat-f2py/issues
Classifier: Operating System :: MacOS :: MacOS X
Classifier: Operating System :: POSIX :: Linux
Classifier: Intended Audience :: Science/Research
Classifier: Programming Language :: Python
Classifier: Programming Language :: Python :: 3
Classifier: Programming Language :: Python :: 3.7
Classifier: Programming Language :: Python :: 3.8
Classifier: Programming Language :: Python :: 3.9
Classifier: Programming Language :: Python :: 3.10
Classifier: Topic :: Scientific/Engineering
Requires-Python: >=3.7
License-File: LICENSE
Requires-Dist: dask[array]
Requires-Dist: numpy (>=1.20.2)
Requires-Dist: xarray
